MANIFEST.in
requirements.txt
setup.py
simple_ostinato/__init__.py
simple_ostinato/constants.py
simple_ostinato/drone.py
simple_ostinato/generator.py
simple_ostinato/port.py
simple_ostinato/stream.py
simple_ostinato/utils.py
simple_ostinato.egg-info/PKG-INFO
simple_ostinato.egg-info/SOURCES.txt
simple_ostinato.egg-info/dependency_links.txt
simple_ostinato.egg-info/requires.txt
simple_ostinato.egg-info/top_level.txt
simple_ostinato/protocols/__init__.py
simple_ostinato/protocols/autogenerates.py
simple_ostinato/protocols/baseclass.py
simple_ostinato/protocols/overrides.py