Metadata-Version: 1.0
Name: simple-ostinato
Version: 0.0.3
Summary: simple ostinato python client
Home-page: http://github.com/little-dude/simple-ostinato
Author: Corentin Henry
Author-email: corentin.henry@gmail.com
License: GPLv3
Platform: UNKNOWN
